mongodriver/__init__.py
mongodriver/async_mongodriver.py
mongodriver/mongodriver.py
mongodriver-1.3.4.dist-info/LICENSE
mongodriver-1.3.4.dist-info/METADATA
mongodriver-1.3.4.dist-info/WHEEL
mongodriver-1.3.4.dist-info/top_level.txt
mongodriver-1.3.4.dist-info/RECORD
