Metadata-Version: 2.1
Name: mongodriver
Version: 1.3.4
Summary: Object-oriented interactions with MongoDB
Home-page: https://github.com/jakestrouse00/mongodriver
Author: Jake Strouse
Author-email: jstrouse@meh.llc
License: MIT
Keywords: mongodb
Classifier: Programming Language :: Python :: 3
Classifier: License :: OSI Approved :: MIT License
Classifier: Operating System :: OS Independent
Requires-Python: >=3.10
License-File: LICENSE
Requires-Dist: pymongo ==4.4.1
Requires-Dist: pymongo[srv] ==4.4.1
Requires-Dist: motor ==3.2.0
Requires-Dist: motor[srv] ==3.2.0
